<settings>
  <data_type>csv</data_type>
  <background>
    <alpha>100</alpha>
    <border_alpha>20</border_alpha>
  </background>
  <grid>
    <category>
      <dashed>1</dashed>
    </category>
    <value>
      <dashed>1</dashed>
      <approx_count>6</approx_count>
      <fill_alpha>100</fill_alpha>
    </value>
  </grid>
  <axes>
    <category>
      <tick_length>0</tick_length>
      <width>0</width>
      <color>99FF00</color>
      <alpha>6</alpha>
    </category>
    <value>
      <tick_length>1</tick_length>
      <width>1</width>
      <color>E7E7E7</color>
      <alpha>7</alpha>
    </value>
  </axes>
  <values>
    <value>
      <min>0</min>
    </value>
  </values>
  <legend>
    <enabled>0</enabled>
  </legend>
  <angle>60</angle>
  <column>
    <width>50</width>
    <spacing>8</spacing>
    <balloon_text>{title}: {value} %</balloon_text>
    <grow_time>3</grow_time>
  </column>
  <graphs>
    <graph gid="0">
      <title>求助率</title>
      <color>ADD981</color>
      <visible_in_legend>0</visible_in_legend>
    </graph>
  </graphs>
  <labels>
    <label lid="0">
      <text></text>
      <y>18</y>
      <text_color>000000</text_color>
      <text_size>13</text_size>
      <align>center</align>
    </label>
  </labels>
  <strings>
      <no_data>数据正在准备中，请稍后再试。</no_data>
      <export_as_image>数据正在准备中，请稍后再试。</export_as_image>
      <error_in_data_file>数据正在准备中，请稍后再试。</error_in_data_file>
      <collecting_data>数据正在准备中，请稍后再试。</collecting_data>
      <wrong_zoom_value>数据正在准备中，请稍后再试。</wrong_zoom_value>
  </strings>
</settings>